LFSR Stream Cipher.srcs/sources_1/new/tt_um_lfsr_cipher.v
/*
 * LFSR Stream Cipher — TinyTapeout Submission
 * IEEE CEDA SSCS Chapter, KIIT University
 *
 * ui_in  [7:0] : 8-bit key input (loaded on rst)
 * uo_out [7:0] : 8-bit keystream output (raw LFSR output)
 * uio    [7:0] : bidirectional — input plaintext, output ciphertext
 * uio_oe [7:0] : set to 0xFF (all outputs) during cipher mode
 *
 * How it works:
 *   1. On reset, LFSR is seeded with {ui_in, 8'hA5} (key + fixed salt)
 *   2. Every clock cycle, LFSR shifts and generates 1 new keystream byte
 *   3. uo_out shows raw keystream
 *   4. uio_out = uio_in XOR keystream (encrypt/decrypt)
 */

module tt_um_lfsr_cipher (
    input  wire [7:0] ui_in,    // 8-bit key
    output wire [7:0] uo_out,   // keystream output
    input  wire [7:0] uio_in,   // plaintext input
    output wire [7:0] uio_out,  // ciphertext output
    output wire [7:0] uio_oe,   // bidirectional direction (1=output)
    input  wire       ena,       // always 1
    input  wire       clk,       // clock
    input  wire       rst_n      // active-low reset
);

    // 16-bit Galois LFSR
    // Taps at positions 16,15,13,4 ? polynomial x^16+x^15+x^13+x^4+1
    // This gives maximum-length sequence of 65535 cycles before repeating
    reg [15:0] lfsr;

    wire feedback = lfsr[0]; // LSB feedback

    always @(posedge clk or negedge rst_n) begin
        if (!rst_n) begin
            // Seed LFSR with key + salt (never seed with 0)
            lfsr <= {ui_in, 8'hA5};
        end else begin
            // Galois LFSR shift with taps
            lfsr <= {1'b0, lfsr[15:1]}          // shift right
                  ^ (feedback ? 16'hB400 : 16'h0); // XOR taps if feedback=1
            // 0xB400 = taps at bits 15,13,12,10 for maximal length
        end
    end

    // Keystream = upper 8 bits of LFSR state
    wire [7:0] keystream = lfsr[15:8];

    // Encrypt: XOR plaintext with keystream
    assign uo_out  = keystream;           // raw keystream visible on output
    assign uio_out = uio_in ^ keystream; // ciphertext = plaintext XOR keystream
    assign uio_oe  = 8'hFF;              // all bidir pins are outputs

endmodule

LFSR Stream Cipher.srcs/sim_1/new/tb_lfsr_cipher.v
`timescale 1ns/1ps

module tb_lfsr_cipher;

    reg        clk, rst_n;
    reg  [7:0] ui_in;   // key
    reg  [7:0] uio_in;  // plaintext
    wire [7:0] uo_out;  // keystream
    wire [7:0] uio_out; // ciphertext
    wire [7:0] uio_oe;

    // Instantiate design
    tt_um_lfsr_cipher uut (
        .clk(clk), .rst_n(rst_n),
        .ui_in(ui_in),
        .uo_out(uo_out),
        .uio_in(uio_in),
        .uio_out(uio_out),
        .uio_oe(uio_oe),
        .ena(1'b1)
    );

    // 10ns clock
    always #5 clk = ~clk;

    integer i;

    initial begin
        $dumpfile("cipher.vcd");
        $dumpvars(0, tb_lfsr_cipher);

        clk   = 0;
        rst_n = 0;
        ui_in = 8'hAB;   // secret key = 0xAB
        uio_in = 8'h48;  // plaintext  = 0x48 ('H')

        // Apply reset for 2 cycles
        #10 rst_n = 1;

        $display("Key = 0x%02X", ui_in);
        $display("Plaintext = 0x%02X ('%c')", uio_in, uio_in);
        $display("-----------------------------");
        $display("Cycle | Keystream | Ciphertext");

        // Run 10 cycles, observe keystream and ciphertext
        for (i = 0; i < 10; i = i + 1) begin
            @(posedge clk);
            #1; // small delay for output to settle
            $display("  %2d  |   0x%02X   |   0x%02X", i, uo_out, uio_out);
        end

        // Now try decryption:
        // Feed ciphertext back in - XOR with same keystream = original plaintext
        $display("\n-- Decryption Test --");
        rst_n = 0; #10 rst_n = 1; // reset to resync keystream

        @(posedge clk); #1;
        uio_in = uio_out; // feed ciphertext in
        @(posedge clk); #1;
        $display("Decrypted = 0x%02X ('%c')", uio_out, uio_out);

        #20 $finish;
    end

endmodule

LFSR Stream Cipher.sim/sim_1/behav/xsim/cipher.vcd
$date
   Mon May 11 02:27:38 2026
$end
$version
  2019.2
$end
$timescale
  1ps
$end
$scope module tb_lfsr_cipher $end
$var reg 1 ! clk $end
$var reg 1 " rst_n $end
$var reg 8 # ui_in [7:0] $end
$var reg 8 $ uio_in [7:0] $end
$var wire 8 % uo_out [7:0] $end
$var wire 8 & uio_out [7:0] $end
$var wire 8 ' uio_oe [7:0] $end
$var integer 32 ( i $end
$scope module uut $end
$var wire 8 ) ui_in [7:0] $end
$var wire 8 % uo_out [7:0] $end
$var wire 8 * uio_in [7:0] $end
$var wire 8 & uio_out [7:0] $end
$var wire 8 ' uio_oe [7:0] $end
$var wire 1 + ena $end
$var wire 1 , clk $end
$var wire 1 - rst_n $end
$var reg 16 . lfsr [15:0] $end
$var wire 1 / feedback $end
$var wire 8 0 keystream [7:0] $end
$upscope $end
$upscope $end
$enddefinitions $end
#0
$dumpvars
0!
0"
b10101011 #
b1001000 $
b10101011 %
b11100011 &
b11111111 '
bx (
b10101011 )
b1001000 *
1+
0,
0-
b1010101110100101 .
1/
b10101011 0
$end
#5000
1!
1,
#10000
0!
1"
b0 (
0,
1-
#15000
1!
b11100001 %
b10101001 &
1,
b1110000111010010 .
0/
b11100001 0
#16000
b1 (
#20000
0!
0,
#25000
1!
b1110000 %
b111000 &
1,
b111000011101001 .
1/
b1110000 0
#26000
b10 (
#30000
0!
0,
#35000
1!
b10001100 %
b11000100 &
1,
b1000110001110100 .
0/
b10001100 0
#36000
b11 (
#40000
0!
0,
#45000
1!
b1000110 %
b1110 &
1,
b100011000111010 .
b1000110 0
#46000
b100 (
#50000
0!
0,
#55000
1!
b100011 %
b1101011 &
1,
b10001100011101 .
1/
b100011 0
#56000
b101 (
#60000
0!
0,
#65000
1!
b10100101 %
b11101101 &
1,
b1010010110001110 .
0/
b10100101 0
#66000
b110 (
#70000
0!
0,
#75000
1!
b1010010 %
b11010 &
1,
b101001011000111 .
1/
b1010010 0
#76000
b111 (
#80000
0!
0,
#85000
1!
b10011101 %
b11010101 &
1,
b1001110101100011 .
b10011101 0
#86000
b1000 (
#90000
0!
0,
#95000
1!
b11111010 %
b10110010 &
1,
b1111101010110001 .
b11111010 0
#96000
b1001 (
#100000
0!
0,
#105000
1!
b11001001 %
b10000001 &
1,
b1100100101011000 .
0/
b11001001 0
#106000
0"
b10101011 %
b11100011 &
b1010 (
0-
b1010101110100101 .
1/
b10101011 0
#110000
0!
0,
#115000
1!
1,
#116000
1"
1-
#120000
0!
0,
#125000
1!
b11100001 %
b10101001 &
1,
b1110000111010010 .
0/
b11100001 0
#126000
b10101001 $
b1001000 &
b10101001 *
#130000
0!
0,
#135000
1!
b1110000 %
b11011001 &
1,
b111000011101001 .
1/
b1110000 0
#140000
0!
0,
#145000
1!
b10001100 %
b100101 &
1,
b1000110001110100 .
0/
b10001100 0
#150000
0!
0,
#155000
1!
b1000110 %
b11101111 &
1,
b100011000111010 .
b1000110 0
